jupyterlab_sublime/__init__.py
jupyterlab_sublime/_version.py
jupyterlab_sublime/labextension/package.json
jupyterlab_sublime/labextension/static/743.317da3d5d9ac3c9e41af.js
jupyterlab_sublime/labextension/static/743.701cd86c1f89cd6cc177.js
jupyterlab_sublime/labextension/static/remoteEntry.2815871f2fdefa03c879.js
jupyterlab_sublime/labextension/static/remoteEntry.39834bb24d7facc6f2b3.js
jupyterlab_sublime/labextension/static/style.js
jupyterlab_sublime-0.4.1.data/data/share/jupyter/labextensions/@ryantam626/jupyterlab_sublime/install.json
jupyterlab_sublime-0.4.1.data/data/share/jupyter/labextensions/@ryantam626/jupyterlab_sublime/package.json
jupyterlab_sublime-0.4.1.data/data/share/jupyter/labextensions/@ryantam626/jupyterlab_sublime/static/743.701cd86c1f89cd6cc177.js
jupyterlab_sublime-0.4.1.data/data/share/jupyter/labextensions/@ryantam626/jupyterlab_sublime/static/remoteEntry.2815871f2fdefa03c879.js
jupyterlab_sublime-0.4.1.data/data/share/jupyter/labextensions/@ryantam626/jupyterlab_sublime/static/style.js
jupyterlab_sublime-0.4.1.dist-info/LICENSE
jupyterlab_sublime-0.4.1.dist-info/METADATA
jupyterlab_sublime-0.4.1.dist-info/WHEEL
jupyterlab_sublime-0.4.1.dist-info/top_level.txt
jupyterlab_sublime-0.4.1.dist-info/RECORD
