Metadata-Version: 2.1
Name: jupyterlab-sublime
Version: 0.4.1
Summary: Sublime notebook cell binding for JupyterLab
Home-page: https://github.com/ryantam626/jupyterlab_sublime.git
Author: Ryan Tam
License: BSD-3-Clause
Keywords: Jupyter,JupyterLab,JupyterLab3
Platform: Linux
Platform: Mac OS X
Platform: Windows
Classifier: License :: OSI Approved :: BSD License
Classifier: Programming Language :: Python
Classifier: Programming Language :: Python :: 3
Classifier: Programming Language :: Python :: 3.6
Classifier: Programming Language :: Python :: 3.7
Classifier: Programming Language :: Python :: 3.8
Classifier: Framework :: Jupyter
Requires-Python: >=3.6
Requires-Dist: jupyterlab (==3.*,>=3.0.0rc13)
